httpmorph/__init__.py
httpmorph/_async.cpython-39-aarch64-linux-gnu.so
httpmorph/_async_client.py
httpmorph/_client_c.py
httpmorph/_http2.cpython-39-aarch64-linux-gnu.so
httpmorph/_httpmorph.cpython-39-aarch64-linux-gnu.so
httpmorph-0.2.7.dist-info/METADATA
httpmorph-0.2.7.dist-info/WHEEL
httpmorph-0.2.7.dist-info/top_level.txt
httpmorph-0.2.7.dist-info/RECORD
