Metadata-Version: 2.1
Name: httpmorph
Version: 0.2.7
Summary: A Python HTTP client focused on mimicking browser fingerprints.
Author-email: Arman Hossain <arman@bytetunnels.com>
License: MIT
Project-URL: Homepage, https://github.com/arman-bd/httpmorph
Project-URL: Documentation, https://github.com/arman-bd/httpmorph/blob/main/README.md
Project-URL: Repository, https://github.com/arman-bd/httpmorph
Project-URL: Issues, https://github.com/arman-bd/httpmorph/issues
Keywords: http,https,client,performance,anti-fingerprint,tls,ja3,http2
Classifier: Development Status :: 3 - Alpha
Classifier: Intended Audience :: Developers
Classifier: License :: OSI Approved :: MIT License
Classifier: Programming Language :: Python :: 3
Classifier: Programming Language :: Python :: 3.8
Classifier: Programming Language :: Python :: 3.9
Classifier: Programming Language :: Python :: 3.10
Classifier: Programming Language :: Python :: 3.11
Classifier: Programming Language :: Python :: 3.12
Classifier: Programming Language :: Python :: 3.13
Classifier: Programming Language :: Python :: 3.14
Classifier: Programming Language :: C
Classifier: Operating System :: OS Independent
Classifier: Operating System :: POSIX :: Linux
Classifier: Operating System :: Microsoft :: Windows
Classifier: Operating System :: MacOS
Classifier: Topic :: Internet :: WWW/HTTP
Classifier: Topic :: Software Development :: Libraries :: Python Modules
Requires-Python: >=3.8
Provides-Extra: build
Requires-Dist: setuptools>=68.0; extra == "build"
Requires-Dist: wheel; extra == "build"
Requires-Dist: Cython>=3.0; extra == "build"
Provides-Extra: dev
Requires-Dist: pytest>=7.0; extra == "dev"
Requires-Dist: pytest-asyncio>=0.21.0; extra == "dev"
Requires-Dist: pytest-benchmark>=4.0; extra == "dev"
Requires-Dist: pytest-cov>=4.0; extra == "dev"
Requires-Dist: cryptography>=41.0; extra == "dev"
Requires-Dist: filelock>=3.12.0; extra == "dev"
Requires-Dist: mypy>=1.0; extra == "dev"
Requires-Dist: ruff>=0.7.0; extra == "dev"
